kipet/__init__.py
kipet/calculation_tools/__init__.py
kipet/calculation_tools/beer_lambert.py
kipet/calculation_tools/diagnostic_tools.py
kipet/calculation_tools/helper.py
kipet/calculation_tools/interpolation.py
kipet/calculation_tools/prob_gen_tools.py
kipet/calculation_tools/reduced_hessian.py
kipet/estimability_tools/__init__.py
kipet/estimability_tools/estimability_analysis.py
kipet/estimability_tools/parameter_handling.py
kipet/estimability_tools/parameter_ranking.py
kipet/estimability_tools/reduced_hessian_parameter_selection.py
kipet/estimator_tools/__init__.py
kipet/estimator_tools/additional_inputs.py
kipet/estimator_tools/estimator_methods.py
kipet/estimator_tools/fe_initialization.py
kipet/estimator_tools/initialize2.py
kipet/estimator_tools/jumps_method.py
kipet/estimator_tools/multiple_experiments.py
kipet/estimator_tools/multiprocessing_kipet.py
kipet/estimator_tools/nested_schur_decomposition.py
kipet/estimator_tools/nsd_step.py
kipet/estimator_tools/parameter_estimator.py
kipet/estimator_tools/pyomo_simulator.py
kipet/estimator_tools/reduced_hessian_methods.py
kipet/estimator_tools/results_object.py
kipet/estimator_tools/variance_estimator.py
kipet/general_settings/__init__.py
kipet/general_settings/settings.py
kipet/general_settings/settings.yml
kipet/general_settings/solver_settings.py
kipet/general_settings/unit_base.py
kipet/general_settings/variable_names.py
kipet/input_output/__init__.py
kipet/input_output/kipet_io.py
kipet/input_output/read_hessian.py
kipet/input_output/read_write_tools.py
kipet/main_modules/__init__.py
kipet/main_modules/reaction_model.py
kipet/main_modules/reaction_set.py
kipet/mixins/__init__.py
kipet/mixins/parameter_estimator_mixins.py
kipet/mixins/wavelength_mixins.py
kipet/model_components/__init__.py
kipet/model_components/component_expression.py
kipet/model_components/data_component.py
kipet/model_components/element_blocks.py
kipet/model_components/expression.py
kipet/model_components/model_components.py
kipet-1.0.72.dist-info/LICENSE
kipet-1.0.72.dist-info/METADATA
kipet-1.0.72.dist-info/WHEEL
kipet-1.0.72.dist-info/top_level.txt
kipet-1.0.72.dist-info/RECORD
