Metadata-Version: 2.1
Name: kipet
Version: 1.0.72
Summary: An all-in-one tool for fitting kinetic models using spectral and other state data
Home-page: UNKNOWN
Author: Kevin McBride, Christina Schenk, Michael Short, Jose Santiago Rodriguez, David M. Thierry, Salvador Garcia-Munoz, Lorenz T. Biegler
Author-email: kevin.w.mcbride.86@gmail.com
Maintainer: Kevin McBride
License: GPL-3.0-or-later
Project-URL: repository, https://github.com/kwmcbride/kipet
Keywords: optimization scientific parameter reaction spectral
Platform: UNKNOWN
Requires-Python: ==3.*,>=3.8.0
Requires-Dist: attrs (==20.*,>=20.3.0)
Requires-Dist: matplotlib (==3.*,>=3.3.4)
Requires-Dist: networkx (==2.7)
Requires-Dist: numpy (==1.*,>=1.20.1)
Requires-Dist: pandas (==1.*,>=1.2.2)
Requires-Dist: pint (==0.*,>=0.16.1)
Requires-Dist: plotly (==4.*,>=4.14.3)
Requires-Dist: pyomo (==6.*,>=6.2)
Requires-Dist: pyyaml (==5.*,>=5.4.1)
Requires-Dist: scipy (==1.*,>=1.6.0)
Requires-Dist: kaleido (==0.2.1)
Requires-Dist: jinja2 (==3.0.1)
Requires-Dist: pytexit (==0.3.4)
Provides-Extra: dev
Requires-Dist: pytest (==5.*,>=5.2.0) ; extra == 'dev'
Requires-Dist: isort (==5.*,>=5.8.0) ; extra == 'dev'
Requires-Dist: mypy (>=0.812) ; extra == 'dev'
Requires-Dist: sphinx-rtd-theme (==0.5.2) ; extra == 'dev'
